jsoncons/__init__.py
jsoncons/cli.py
jsoncons-1.1.0.dist-info/licenses/LICENSE
tests/__init__.py
tests/test_cli.py
jsoncons-1.1.0.dist-info/METADATA
jsoncons-1.1.0.dist-info/WHEEL
jsoncons-1.1.0.dist-info/entry_points.txt
jsoncons-1.1.0.dist-info/top_level.txt
jsoncons-1.1.0.dist-info/RECORD
