Metadata-Version: 2.4
Name: jsoncons
Version: 1.1.0
Summary: A simple CLI tool for validating and formatting JSON data.
Author-email: David Anderson <fapulito@gmail.com>
License: MIT License
Project-URL: Homepage, https://pypi.org/project/jsoncons/
Project-URL: Issues, https://github.com/fapulito/jsoncons/issues
Classifier: Programming Language :: Python :: 3
Classifier: License :: OSI Approved :: MIT License
Classifier: Operating System :: OS Independent
Classifier: Topic :: Utilities
Classifier: Environment :: Console
Requires-Python: >=3.7
License-File: LICENSE
Dynamic: license-file
